txp/.DS_Store
txp/__init__.py
txp/__main__.py
txp/cli.py
txp/cloud/README.md
txp/cloud/__init__.py
txp/cloud/cloud_functions/.DS_Store
txp/cloud/cloud_functions/__init__.py
txp/cloud/cloud_functions/compute_asset_total_worked_time/__init__.py
txp/cloud/cloud_functions/compute_asset_total_worked_time/dist/txp-0.3.3-py3-none-any.whl
txp/cloud/cloud_functions/compute_asset_total_worked_time/main.py
txp/cloud/cloud_functions/compute_asset_total_worked_time/readme.md
txp/cloud/cloud_functions/compute_asset_total_worked_time/requirements.txt
txp/cloud/cloud_functions/ml_notifications/README.md
txp/cloud/cloud_functions/ml_notifications/__init__.py
txp/cloud/cloud_functions/ml_notifications/main.py
txp/cloud/cloud_functions/ml_notifications/requirements.txt
txp/cloud/cloud_functions/paired_devices_cloud_update/.DS_Store
txp/cloud/cloud_functions/paired_devices_cloud_update/__init__.py
txp/cloud/cloud_functions/paired_devices_cloud_update/dist/.DS_Store
txp/cloud/cloud_functions/paired_devices_cloud_update/main.py
txp/cloud/cloud_functions/paired_devices_cloud_update/readme.md
txp/cloud/cloud_functions/paired_devices_cloud_update/requirements.txt
txp/cloud/cloud_functions/state_event_pubsub_to_firestore/__init__.py
txp/cloud/cloud_functions/state_event_pubsub_to_firestore/dist/readme.txt
txp/cloud/cloud_functions/state_event_pubsub_to_firestore/edges_states_schema.json
txp/cloud/cloud_functions/state_event_pubsub_to_firestore/main.py
txp/cloud/cloud_functions/state_event_pubsub_to_firestore/readme.md
txp/cloud/cloud_functions/state_event_pubsub_to_firestore/requirements.txt
txp/cloud/cloud_functions/store_telemetry_event_to_data_lake/README.md
txp/cloud/cloud_functions/store_telemetry_event_to_data_lake/__init__.py
txp/cloud/cloud_functions/store_telemetry_event_to_data_lake/main.py
txp/cloud/cloud_functions/store_telemetry_event_to_data_lake/requirements.txt
txp/cloud/cloud_functions/store_telemetry_event_to_data_lake/test/__init__.py
txp/cloud/pipelines/sections/realtime_pipeline/pub_sub_to_bigquery.egg-info/PKG-INFO
txp/cloud/pipelines/sections/realtime_pipeline/pub_sub_to_bigquery.egg-info/SOURCES.txt
txp/cloud/pipelines/sections/realtime_pipeline/pub_sub_to_bigquery.egg-info/dependency_links.txt
txp/cloud/pipelines/sections/realtime_pipeline/pub_sub_to_bigquery.egg-info/requires.txt
txp/cloud/pipelines/sections/realtime_pipeline/pub_sub_to_bigquery.egg-info/top_level.txt
txp/cloud/pipelines/telemetry/realtime_pipeline/pub_sub_to_bigquery.egg-info/PKG-INFO
txp/cloud/pipelines/telemetry/realtime_pipeline/pub_sub_to_bigquery.egg-info/SOURCES.txt
txp/cloud/pipelines/telemetry/realtime_pipeline/pub_sub_to_bigquery.egg-info/dependency_links.txt
txp/cloud/pipelines/telemetry/realtime_pipeline/pub_sub_to_bigquery.egg-info/requires.txt
txp/cloud/pipelines/telemetry/realtime_pipeline/pub_sub_to_bigquery.egg-info/top_level.txt
txp-0.3.4.dist-info/entry_points.txt
txp-0.3.4.dist-info/WHEEL
txp-0.3.4.dist-info/METADATA
txp-0.3.4.dist-info/RECORD
