Metadata-Version: 2.1
Name: txp
Version: 0.3.4
Summary: Txp is the main Python Package from Tranxpert predictive maintenance solution
Home-page: https://github.com/Traxpert/txp
Keywords: IOT,IIOT,Predictive Maintenance
Author: Tranxpert
Requires-Python: >=3.7,<4.0
Classifier: Programming Language :: Python :: 3
Classifier: Programming Language :: Python :: 3.10
Classifier: Programming Language :: Python :: 3.7
Classifier: Programming Language :: Python :: 3.8
Classifier: Programming Language :: Python :: 3.9
Provides-Extra: cloud
Provides-Extra: dev
Provides-Extra: gateway
Provides-Extra: ml
Requires-Dist: Markdown (>=3.3.6,<4.0.0)
Requires-Dist: PyJWT (>=2.1.0,<3.0.0); extra == "gateway"
Requires-Dist: black (>=21.6b0,<22.0); extra == "dev"
Requires-Dist: colorama (>=0.4.5,<0.5.0)
Requires-Dist: cronsim (>=2.3,<3.0); extra == "cloud"
Requires-Dist: cryptography (>=35.0.0,<36.0.0); extra == "gateway"
Requires-Dist: deepdiff (>=5.7.0,<6.0.0); extra == "gateway"
Requires-Dist: dynaconf (>=3.1.4,<4.0.0)
Requires-Dist: fastapi (>=0.78.0,<0.79.0); extra == "ml"
Requires-Dist: firebase-admin (>=5.2.0,<6.0.0)
Requires-Dist: fpdf (>=1.7.2,<2.0.0); extra == "cloud"
Requires-Dist: freezegun (>=1.1.0,<2.0.0); extra == "gateway"
Requires-Dist: google (>=3.0.0,<4.0.0); extra == "dev"
Requires-Dist: google-api-python-client (>=2.23.0,<3.0.0); extra == "dev"
Requires-Dist: google-auth (>=2.2.1,<3.0.0); extra == "dev"
Requires-Dist: google-auth-oauthlib (>=0.4.6,<0.5.0); extra == "dev"
Requires-Dist: google-cloud-bigquery (>=2.31.0,<3.0.0); python_version >= "3.7" and python_version < "3.11"
Requires-Dist: google-cloud-firestore (>=2.3.0,<3.0.0); extra == "dev"
Requires-Dist: google-cloud-iot (>=2.3.0,<3.0.0); extra == "dev"
Requires-Dist: google-cloud-pubsub (>=2.12.1,<3.0.0); extra == "dev"
Requires-Dist: ifaddr (>=0.1.7,<0.2.0); extra == "gateway"
Requires-Dist: jupyterlab (>=3.4.5,<4.0.0); extra == "dev"
Requires-Dist: kaleido (==0.2.0); extra == "cloud" or extra == "ml"
Requires-Dist: matplotlib
Requires-Dist: mcp9600 (>=0.0.4,<0.0.5); extra == "gateway"
Requires-Dist: nbmake (>=1.3.4,<2.0.0); extra == "dev"
Requires-Dist: numpy (>=1.21.2,<2.0.0); python_version >= "3.7" and python_version < "3.11"
Requires-Dist: opencv-python-headless (>=4.5.5,<5.0.0)
Requires-Dist: paho-mqtt (>=1.5.1,<2.0.0); extra == "gateway"
Requires-Dist: pandas (==1.3.5); python_full_version >= "3.7.1" and python_version < "4.0"
Requires-Dist: plotly (>=5.6.0,<6.0.0)
Requires-Dist: prophet (>=1.1,<2.0); extra == "cloud" or extra == "ml"
Requires-Dist: protobuf (==3.20.0)
Requires-Dist: psutil (>=5.8.0,<6.0.0); extra == "gateway"
Requires-Dist: pydantic (>=1.9.1,<2.0.0)
Requires-Dist: pyserial (>=3.5,<4.0)
Requires-Dist: pytest (>=6.2.4,<7.0.0); extra == "dev"
Requires-Dist: pytest-xdist (>=2.4.0,<3.0.0); extra == "dev"
Requires-Dist: pytz (>=2022.1.0,<2023.0.0)
Requires-Dist: pyudev (>=0.23.1,<0.24.0); extra == "gateway"
Requires-Dist: queuelib (>=1.6.2,<2.0.0); extra == "gateway"
Requires-Dist: ray (>=1.12.0,<2.0.0); extra == "ml"
Requires-Dist: requests (>=2.26.0,<3.0.0); extra == "cloud" or extra == "gateway"
Requires-Dist: schedule (>=1.1.0,<2.0.0); extra == "gateway"
Requires-Dist: scipy (>=1.4.0,<2.0.0); extra == "cloud"
Requires-Dist: six (>=1.13.0,<2.0.0); extra == "gateway"
Requires-Dist: sklearn (>=0.0,<0.1); extra == "ml"
Requires-Dist: streamlit (==1.4.0)
Requires-Dist: streamlit-aggrid (>=0.2.3,<0.3.0); python_full_version >= "3.7.1" and python_version < "4.0"
Requires-Dist: tabulate (>=0.8.9,<0.9.0)
Requires-Dist: transitions (>=0.8.8,<0.9.0); extra == "gateway"
Requires-Dist: xgboost (>=1.6.0,<2.0.0); extra == "ml"
Project-URL: Repository, https://github.com/Traxpert/txp
